pricetool/__init__.py
pricetool/hooks.py
pricetool/read.py
pricetool/run.py
pricetool/sql.py
pricetool/pipelines/__init__.py
pricetool/pipelines/clean.py
pricetool/pipelines/data_engineering/__init__.py
pricetool/pipelines/data_engineering/nodes.py
pricetool/pipelines/data_engineering/nodes_bkp.py
pricetool/pipelines/data_engineering/pipeline.py
pricetool/pipelines/data_engineering/test.py
pricetool/pipelines/data_engineering/test1.py
pricetool/pipelines/data_science/__init__.py
pricetool/pipelines/data_science/nodes.py
pricetool/pipelines/data_science/pipeline.py
pricetool/utils/__init__.py
pricetool/utils/util.py
tests/pipelines/__init__.py
pricetool-0.1.dist-info/METADATA
pricetool-0.1.dist-info/WHEEL
pricetool-0.1.dist-info/entry_points.txt
pricetool-0.1.dist-info/top_level.txt
pricetool-0.1.dist-info/RECORD
