Metadata-Version: 2.1
Name: pricetool
Version: 0.1
Summary: UNKNOWN
Home-page: UNKNOWN
License: UNKNOWN
Platform: UNKNOWN
Requires-Dist: anyconfig (==0.9.11)
Requires-Dist: appdirs (==1.4.4)
Requires-Dist: argon2-cffi (==20.1.0)
Requires-Dist: arrow (==0.17.0)
Requires-Dist: async-generator (==1.10)
Requires-Dist: atomicwrites (==1.4.0)
Requires-Dist: attrs (==20.3.0)
Requires-Dist: backcall (==0.2.0)
Requires-Dist: binaryornot (==0.4.4)
Requires-Dist: black (==v19.10b0)
Requires-Dist: bleach (==3.2.1)
Requires-Dist: cachetools (==4.1.1)
Requires-Dist: certifi (==2020.11.8)
Requires-Dist: cffi (==1.14.4)
Requires-Dist: chardet (==3.0.4)
Requires-Dist: click (==7.1.2)
Requires-Dist: colorama (==0.4.4)
Requires-Dist: cookiecutter (==1.6.0)
Requires-Dist: coverage (==5.3)
Requires-Dist: decorator (==4.4.2)
Requires-Dist: defusedxml (==0.6.0)
Requires-Dist: entrypoints (==0.3)
Requires-Dist: flake8 (==3.8.4)
Requires-Dist: fsspec (==0.6.3)
Requires-Dist: future (==0.18.2)
Requires-Dist: idna (==2.10)
Requires-Dist: ipykernel (==5.3.4)
Requires-Dist: ipython-genutils (==0.2.0)
Requires-Dist: ipython (==7.19.0)
Requires-Dist: ipywidgets (==7.5.1)
Requires-Dist: isort (==4.3.21)
Requires-Dist: jedi (==0.17.2)
Requires-Dist: jinja2-time (==0.2.0)
Requires-Dist: jinja2 (==2.11.2)
Requires-Dist: jmespath (==0.10.0)
Requires-Dist: jsonschema (==3.2.0)
Requires-Dist: jupyter-client (==6.1.7)
Requires-Dist: jupyter-console (==6.2.0)
Requires-Dist: jupyter-core (==4.7.0)
Requires-Dist: jupyter (==1.0.0)
Requires-Dist: jupyterlab-launcher (==0.10.5)
Requires-Dist: jupyterlab-pygments (==0.1.2)
Requires-Dist: jupyterlab (==0.31.1)
Requires-Dist: kedro[pandas.csvdataset] (==0.16.6)
Requires-Dist: markupsafe (==1.1.1)
Requires-Dist: mccabe (==0.6.1)
Requires-Dist: mistune (==0.8.4)
Requires-Dist: more-itertools (==8.6.0)
Requires-Dist: nbclient (==0.5.1)
Requires-Dist: nbconvert (==6.0.7)
Requires-Dist: nbformat (==5.0.8)
Requires-Dist: nbstripout (==0.3.3)
Requires-Dist: nest-asyncio (==1.4.3)
Requires-Dist: notebook (==6.1.5)
Requires-Dist: numpy (==1.19.4)
Requires-Dist: packaging (==20.7)
Requires-Dist: pandas (==1.1.4)
Requires-Dist: pandocfilters (==1.4.3)
Requires-Dist: parso (==0.7.1)
Requires-Dist: pathspec (==0.8.1)
Requires-Dist: pickleshare (==0.7.5)
Requires-Dist: pip-tools (==5.4.0)
Requires-Dist: pluggy (==0.13.1)
Requires-Dist: poyo (==0.5.0)
Requires-Dist: prometheus-client (==0.9.0)
Requires-Dist: prompt-toolkit (==3.0.8)
Requires-Dist: py (==1.9.0)
Requires-Dist: pycodestyle (==2.6.0)
Requires-Dist: pycparser (==2.20)
Requires-Dist: pyflakes (==2.2.0)
Requires-Dist: pygments (==2.7.2)
Requires-Dist: pyparsing (==2.4.7)
Requires-Dist: pyrsistent (==0.17.3)
Requires-Dist: pytest-cov (==2.10.1)
Requires-Dist: pytest-mock (==1.13.0)
Requires-Dist: pytest (==5.4.3)
Requires-Dist: python-dateutil (==2.8.1)
Requires-Dist: python-json-logger (==0.1.11)
Requires-Dist: pytz (==2020.4)
Requires-Dist: pywin32 (==300)
Requires-Dist: pywinpty (==0.5.7)
Requires-Dist: pyyaml (==5.3.1)
Requires-Dist: pyzmq (==20.0.0)
Requires-Dist: qtconsole (==5.0.1)
Requires-Dist: qtpy (==1.9.0)
Requires-Dist: regex (==2020.11.13)
Requires-Dist: requests (==2.25.0)
Requires-Dist: send2trash (==1.5.0)
Requires-Dist: six (==1.15.0)
Requires-Dist: terminado (==0.9.1)
Requires-Dist: testpath (==0.4.4)
Requires-Dist: toml (==0.10.2)
Requires-Dist: toposort (==1.5)
Requires-Dist: tornado (==6.1)
Requires-Dist: traitlets (==5.0.5)
Requires-Dist: typed-ast (==1.4.1)
Requires-Dist: urllib3 (==1.26.2)
Requires-Dist: wcwidth (==0.2.5)
Requires-Dist: webencodings (==0.5.1)
Requires-Dist: wheel (==0.32.2)
Requires-Dist: whichcraft (==0.6.1)
Requires-Dist: widgetsnbextension (==3.5.1)
Provides-Extra: docs
Requires-Dist: sphinx (<2.0,>=1.6.3); extra == 'docs'
Requires-Dist: sphinx-rtd-theme (==0.4.1); extra == 'docs'
Requires-Dist: nbsphinx (==0.3.4); extra == 'docs'
Requires-Dist: nbstripout (==0.3.3); extra == 'docs'
Requires-Dist: recommonmark (==0.5.0); extra == 'docs'
Requires-Dist: sphinx-autodoc-typehints (==1.6.0); extra == 'docs'
Requires-Dist: sphinx-copybutton (==0.2.5); extra == 'docs'
Requires-Dist: jupyter-client (<7.0,>=5.1.0); extra == 'docs'
Requires-Dist: tornado (<6.0,>=4.2); extra == 'docs'
Requires-Dist: ipykernel (<5.0,>=4.8.1); extra == 'docs'
